{
  "updated_at": "2026-07-18 12:52",
  "has_alert": false,
  "items": [
    {
      "category": "news",
      "label": "ニュース",
      "text": "【大雨被害】栃木 土砂流れ込み住宅倒壊 夫婦と連絡取れず",
      "source": "NHK",
      "time": "Sat, 18 Jul 2026 11:58:05 +0900",
      "image": "https://imgu.web.nhk/news/u/news/html/20260718/K10015179921_2607181026_0718103849_01_02.jpg"
    },
    {
      "category": "news",
      "label": "ニュース",
      "text": "千葉 点滴殺人 元職員が死亡患者の病室を複数回出入りか",
      "source": "NHK",
      "time": "Sat, 18 Jul 2026 11:57:10 +0900",
      "image": "https://imgu.web.nhk/news/u/news/html/20260718/K10015180141_2607181133_0718115710_01_02.jpg"
    },
    {
      "category": "news",
      "label": "ニュース",
      "text": "京アニ放火殺人事件から7年 スタジオ跡地で追悼式 京都",
      "source": "NHK",
      "time": "Sat, 18 Jul 2026 11:45:59 +0900",
      "image": "https://imgu.web.nhk/news/u/news/html/20260718/K10015179541_2607181137_0718114600_01_02.jpg"
    },
    {
      "category": "news",
      "label": "ニュース",
      "text": "米アップル 日本でiPhoneの販売価格を約10％値上げ",
      "source": "NHK",
      "time": "Sat, 18 Jul 2026 12:40:21 +0900",
      "image": "https://imgu.web.nhk/news/u/news/html/20260718/K10015180171_2607181218_0718124022_01_02.jpg"
    },
    {
      "category": "news",
      "label": "ニュース",
      "text": "ドジャース佐々木 ヤンキース戦6回途中1失点 大谷無安打",
      "source": "NHK",
      "time": "Sat, 18 Jul 2026 12:44:31 +0900",
      "image": "https://imgu.web.nhk/news/u/news/html/20260718/K10015180161_2607181233_0718124431_01_03.jpg"
    },
    {
      "category": "news",
      "label": "ニュース",
      "text": "栃木 群馬で記録的大雨 きょうも北～西日本で雷雨か 十分注意",
      "source": "NHK",
      "time": "Sat, 18 Jul 2026 06:13:58 +0900"
    },
    {
      "category": "news",
      "label": "ニュース",
      "text": "W杯 アルゼンチン監督が決意「最高のパフォーマンス発揮を」",
      "source": "NHK",
      "time": "Sat, 18 Jul 2026 12:35:52 +0900"
    }
  ]
}